pyls_cwrap/__about__.py
pyls_cwrap/__init__.py
pyls_cwrap/plugin.py
pyls_cwrap-1.0.3.dist-info/LICENSE
pyls_cwrap-1.0.3.dist-info/METADATA
pyls_cwrap-1.0.3.dist-info/WHEEL
pyls_cwrap-1.0.3.dist-info/entry_points.txt
pyls_cwrap-1.0.3.dist-info/top_level.txt
pyls_cwrap-1.0.3.dist-info/RECORD
