Metadata-Version: 2.1
Name: pyls-cwrap
Version: 1.0.3
Summary: cwrap plugin for python-language-server
Home-page: https://github.com/daizutabi/pyls-cwrap
Author: daizutabi
Author-email: daizutabi@gmail.com
License: MIT
Platform: Any
Provides: pyls_cwrap
Requires-Dist: python-language-server
Requires-Dist: pheasant
